{
    "section1": {
        "files": [
            {
                "url": [
                    "assets/sounds/player_jump.mp3"
                ],
                "type": "audio",
                "key": "player_jump"
            },
            {
                "url": [
                    "assets/sounds/UI-Sounds/quest_accept.wav"
                ],
                "type": "audio",
                "key": "quest_accept"
            },
            {
                "url": [
                    "assets/sounds/UI-Sounds/quest_button_hover.mp3"
                ],
                "type": "audio",
                "key": "quest_button_hover"
            },
            {
                "url": [
                    "assets/sounds/UI-Sounds/quest_close.wav"
                ],
                "type": "audio",
                "key": "quest_close"
            },
            {
                "url": [
                    "assets/sounds/UI-Sounds/quest_complete.mp3"
                ],
                "type": "audio",
                "key": "quest_complete"
            },
            {
                "url": [
                    "assets/sounds/UI-Sounds/quest_decline.wav"
                ],
                "type": "audio",
                "key": "quest_decline"
            },
            {
                "url": [
                    "assets/sounds/UI-Sounds/quest_open.wav"
                ],
                "type": "audio",
                "key": "quest_open"
            },
            {
                "url": [
                    "assets/sounds/UI-Sounds/soft_click.wav"
                ],
                "type": "audio",
                "key": "soft_click"
            }
        ]
    },
    "meta": {
        "app": "Phaser Editor 2D - Asset Pack Editor",
        "contentType": "phasereditor2d.pack.core.AssetContentType",
        "url": "https://phasereditor2d.com",
        "version": 2,
        "showAllFilesInBlocks": false
    }
}